statescale/__about__.py
statescale/__init__.py
statescale/_containers.py
statescale/_evaluate.py
statescale/_snapshot.py
statescale/kernels/__init__.py
statescale/kernels/griddata.py
statescale/kernels/surrogate.py
statescale-0.2.2.dist-info/licenses/LICENSE
statescale-0.2.2.dist-info/METADATA
statescale-0.2.2.dist-info/WHEEL
statescale-0.2.2.dist-info/top_level.txt
statescale-0.2.2.dist-info/RECORD
