Metadata-Version: 2.4
Name: statescale
Version: 0.2.2
Summary: snapshot-driven state upscaling
Author-email: Andreas Dutzler <a.dutzler@gmail.com>
License-Expression: MIT
Project-URL: Homepage, https://statescale.readthedocs.io/en/latest
Project-URL: Documentation, https://statescale.readthedocs.io/en/latest
Project-URL: Repository, https://github.com/adtzlr/statescale
Project-URL: Issues, https://github.com/adtzlr/statescale/issues
Project-URL: Changelog, https://github.com/adtzlr/statescale/blob/main/CHANGELOG.md
Keywords: computational-mechanics,interpolation,surrogate-model,python,scientific-computing,solid-mechanics-codes
Classifier: Development Status :: 5 - Production/Stable
Classifier: Programming Language :: Python
Classifier: Intended Audience :: Science/Research
Classifier: Operating System :: OS Independent
Classifier: Programming Language :: Python
Classifier: Programming Language :: Python :: 3
Classifier: Programming Language :: Python :: 3.10
Classifier: Programming Language :: Python :: 3.11
Classifier: Programming Language :: Python :: 3.12
Classifier: Programming Language :: Python :: 3.13
Classifier: Programming Language :: Python :: 3.14
Classifier: Topic :: Scientific/Engineering
Classifier: Topic :: Scientific/Engineering :: Mathematics
Classifier: Topic :: Utilities
Requires-Python: >=3.10
License-File: LICENSE
Requires-Dist: numpy
Requires-Dist: scipy
Provides-Extra: docs
Requires-Dist: pydata-sphinx-theme; extra == "docs"
Requires-Dist: sphinx-autoapi; extra == "docs"
Requires-Dist: sphinx-inline-tabs; extra == "docs"
Requires-Dist: sphinx-copybutton; extra == "docs"
Requires-Dist: sphinx-design; extra == "docs"
Requires-Dist: sphinx-gallery; extra == "docs"
Requires-Dist: pypandoc; extra == "docs"
Provides-Extra: examples
Requires-Dist: felupe; extra == "examples"
Requires-Dist: pyvista[jupyter]; extra == "examples"
Requires-Dist: matplotlib; extra == "examples"
Requires-Dist: meshio; extra == "examples"
Provides-Extra: dev
Requires-Dist: pytest; extra == "dev"
Requires-Dist: tox; extra == "dev"
Dynamic: license-file
